LICENSE
MANIFEST.in
README.md
setup.py
basiccrawler/__init__.py
basiccrawler/crawler.py
basiccrawler.egg-info/PKG-INFO
basiccrawler.egg-info/SOURCES.txt
basiccrawler.egg-info/dependency_links.txt
basiccrawler.egg-info/not-zip-safe
basiccrawler.egg-info/requires.txt
basiccrawler.egg-info/top_level.txt
docs/data_model.md
docs/design.md