Metadata-Version: 1.1
Name: basiccrawler
Version: 0.1.2
Summary: Basic web crawler that automates website exploration and producing web resource trees.
Home-page: https://github.com/learningequality/BasicCrawler
Author: Learning Equality
Author-email: ivan@learningequalty.org
License: MIT license
Keywords: basiccrawler
Platform: UNKNOWN
Classifier: Development Status :: 2 - Pre-Alpha
Classifier: Intended Audience :: Developers
Classifier: License :: OSI Approved :: MIT License
Classifier: Natural Language :: English
Classifier: Programming Language :: Python :: 3
Classifier: Programming Language :: Python :: 3.4
Classifier: Programming Language :: Python :: 3.5
